av/utils.pxd
av/dictionary.cpython-311-darwin.so
av/frame.pxd
av/plane.pyx
av/dictionary.pyx
av/descriptor.pxd
av/descriptor.cpython-311-darwin.so
av/packet.pyi
av/buffer.pyi
av/error.pyi
av/logging.pxd
av/plane.cpython-311-darwin.so
av/format.pxd
av/_core.pyi
av/bitstream.pxd
av/bitstream.pyi
av/format.pyi
av/opaque.cpython-311-darwin.so
av/__init__.pxd
av/stream.cpython-311-darwin.so
av/logging.cpython-311-darwin.so
av/logging.pyi
av/error.pxd
av/bytesource.cpython-311-darwin.so
av/datasets.py
av/buffer.pxd
av/packet.pxd
av/__init__.py
av/descriptor.pyi
av/option.pyx
av/bytesource.pxd
av/about.py
av/frame.pyi
av/stream.py
av/opaque.pxd
av/opaque.pyx
av/bytesource.pyx
av/plane.pyi
av/dictionary.pyi
av/option.pxd
av/buffer.pyx
av/frame.cpython-311-darwin.so
av/utils.cpython-311-darwin.so
av/utils.py
av/error.pyx
av/frame.py
av/bitstream.cpython-311-darwin.so
av/py.typed
av/_core.pyx
av/stream.pxd
av/packet.py
av/_core.cpython-311-darwin.so
av/stream.pyi
av/bitstream.pyx
av/error.cpython-311-darwin.so
av/option.cpython-311-darwin.so
av/format.pyx
av/logging.pyx
av/format.cpython-311-darwin.so
av/packet.cpython-311-darwin.so
av/dictionary.pxd
av/option.pyi
av/__main__.py
av/descriptor.pyx
av/plane.pxd
av/buffer.cpython-311-darwin.so
av/video/frame.pxd
av/video/plane.pyx
av/video/codeccontext.cpython-311-darwin.so
av/video/reformatter.cpython-311-darwin.so
av/video/plane.cpython-311-darwin.so
av/video/reformatter.pxd
av/video/format.pxd
av/video/__init__.pyi
av/video/reformatter.pyi
av/video/format.pyi
av/video/__init__.pxd
av/video/stream.cpython-311-darwin.so
av/video/codeccontext.pyx
av/video/__init__.py
av/video/frame.pyi
av/video/stream.py
av/video/plane.pyi
av/video/frame.cpython-311-darwin.so
av/video/codeccontext.pxd
av/video/frame.py
av/video/stream.pxd
av/video/stream.pyi
av/video/format.pyx
av/video/reformatter.pyx
av/video/format.cpython-311-darwin.so
av-16.0.0.dist-info/RECORD
av-16.0.0.dist-info/WHEEL
av-16.0.0.dist-info/entry_points.txt
av-16.0.0.dist-info/top_level.txt
av-16.0.0.dist-info/METADATA
av-16.0.0.dist-info/licenses/AUTHORS.rst
av-16.0.0.dist-info/licenses/AUTHORS.py
av-16.0.0.dist-info/licenses/LICENSE.txt
